setup.py
balu_distributions/Binomialdistribution.py
balu_distributions/Gaussiandistribution.py
balu_distributions/Generaldistribution.py
balu_distributions/__init__.py
balu_distributions.egg-info/PKG-INFO
balu_distributions.egg-info/SOURCES.txt
balu_distributions.egg-info/dependency_links.txt
balu_distributions.egg-info/not-zip-safe
balu_distributions.egg-info/top_level.txt